LICENSE
MANIFEST.in
README.md
setup.py
pocket/__init__.py
pocket_api.egg-info/PKG-INFO
pocket_api.egg-info/SOURCES.txt
pocket_api.egg-info/dependency_links.txt
pocket_api.egg-info/requires.txt
pocket_api.egg-info/top_level.txt