Metadata-Version: 1.0
Name: pocket-api
Version: 0.1.5
Summary: A python wrapper around GetPocket API V3. 
Home-page: https://github.com/rakanalh/pocket-api
Author: Rakan Alhneiti
Author-email: rakan.alhneiti@gmail.com
License: LICENSE
Platform: UNKNOWN
